LICENSE
MANIFEST.in
README.rst
setup.py
embiggen/__init__.py
embiggen/__version__.py
embiggen.egg-info/PKG-INFO
embiggen.egg-info/SOURCES.txt
embiggen.egg-info/dependency_links.txt
embiggen.egg-info/requires.txt
embiggen.egg-info/top_level.txt
embiggen/edge_label_prediction/__init__.py
embiggen/edge_label_prediction/edge_label_prediction_evaluation.py
embiggen/edge_label_prediction/edge_label_prediction_model.py
embiggen/edge_label_prediction/sklearn_like_edge_label_prediction_adapter.py
embiggen/edge_label_prediction/edge_label_prediction_catboost/__init__.py
embiggen/edge_label_prediction/edge_label_prediction_catboost/catboost_edge_label_prediction.py
embiggen/edge_label_prediction/edge_label_prediction_lightgbm/__init__.py
embiggen/edge_label_prediction/edge_label_prediction_lightgbm/lgbm_edge_label_prediction.py
embiggen/edge_label_prediction/edge_label_prediction_lleaves/__init__.py
embiggen/edge_label_prediction/edge_label_prediction_lleaves/lleaves_edge_label_prediction.py
embiggen/edge_label_prediction/edge_label_prediction_sklearn/__init__.py
embiggen/edge_label_prediction/edge_label_prediction_sklearn/decision_tree_edge_label_prediction.py
embiggen/edge_label_prediction/edge_label_prediction_sklearn/extra_trees_edge_label_prediction.py
embiggen/edge_label_prediction/edge_label_prediction_sklearn/gradient_boosting_edge_label_prediction.py
embiggen/edge_label_prediction/edge_label_prediction_sklearn/hist_gradient_boosting_edge_label_prediction.py
embiggen/edge_label_prediction/edge_label_prediction_sklearn/k_neighbours_edge_label_prediction.py
embiggen/edge_label_prediction/edge_label_prediction_sklearn/linear_svc_edge_label_prediction.py
embiggen/edge_label_prediction/edge_label_prediction_sklearn/logistic_regression_cv_edge_label_prediction.py
embiggen/edge_label_prediction/edge_label_prediction_sklearn/mlp_edge_label_prediction.py
embiggen/edge_label_prediction/edge_label_prediction_sklearn/nu_svc_edge_label_prediction.py
embiggen/edge_label_prediction/edge_label_prediction_sklearn/radius_neighbours_edge_label_prediction.py
