Metadata-Version: 2.1
Name: embiggen
Version: 0.11.96
Summary: 🍇 Embiggen is the Python Graph Representation learning, Prediction and Evaluation module processing submodule of the GRAPE library.
Home-page: https://github.com/monarch-initiative/embiggen
Author: Vida Ravanmehr, Peter Robinson, Luca Cappelletti, Tommaso Fontana
Author-email: vida.ravanmehr@jax.org, peter.robinson@jax.org, luca.cappelletti1@unimi.it, tommaso.fontana@mail.polimi.it
License: BSD3
Keywords: Graph Representation Learning,LINE,TransE,Node2Vec,DeeWalk
Requires-Python: >=3.8.0
License-File: LICENSE
Requires-Dist: numpy
Requires-Dist: pandas
Requires-Dist: Jinja2
Requires-Dist: tqdm
Requires-Dist: humanize
Requires-Dist: matplotlib>=3.5.2
Requires-Dist: scikit-learn>=1.2
Requires-Dist: dict_hash>=1.1.32
Requires-Dist: userinput>=1.0.20
Requires-Dist: ddd_subplots>=1.0.27
Requires-Dist: sanitize_ml_labels>=1.0.50
Requires-Dist: keras_mixed_sequence>=1.0.28
Requires-Dist: ensmallen>=0.8.94
Requires-Dist: environments_utils>=1.0.10
Requires-Dist: compress_pickle>=2.1.0
Requires-Dist: validate_version_code
Requires-Dist: cache_decorator>=2.1.14
Requires-Dist: threadpoolctl>=3.1.0
Requires-Dist: pydot
Requires-Dist: compress_pickle>=2.1.0
Requires-Dist: packaging
Provides-Extra: test
Requires-Dist: codacy-coverage; extra == "test"
Requires-Dist: coveralls; extra == "test"
Requires-Dist: pytest; extra == "test"
Requires-Dist: pytest-cov; extra == "test"
Requires-Dist: validate_version_code; extra == "test"
Requires-Dist: pylint; extra == "test"
Requires-Dist: silence_tensorflow; extra == "test"
